[
  {
    "id": "65c19a43-189c-44f0-86b6-23815d1ef810",
    "data": [
      {
        "text": "I\u0027ll be back in a few minutes",
        "userDefined": false
      }
    ],
    "isTemplate": false,
    "count": 0,
    "updated": 0
  },
  {
    "id": "bf135676-8b9e-4f80-9206-d2b64b1b0953",
    "data": [
      {
        "text": "be back ",
        "userDefined": false
      },
      {
        "text": "in",
        "meta": "@sys.ignore",
        "userDefined": false
      },
      {
        "text": " ",
        "userDefined": false
      },
      {
        "text": "5",
        "meta": "@sys.ignore",
        "userDefined": false
      },
      {
        "text": " minutes",
        "userDefined": false
      }
    ],
    "isTemplate": false,
    "count": 0,
    "updated": 0
  },
  {
    "id": "5789223f-6940-4735-be58-bc434b7c50ff",
    "data": [
      {
        "text": "I\u0027ll get back to you ",
        "userDefined": false
      },
      {
        "text": "in",
        "meta": "@sys.ignore",
        "userDefined": false
      },
      {
        "text": " a moment",
        "userDefined": false
      }
    ],
    "isTemplate": false,
    "count": 0,
    "updated": 0
  },
  {
    "id": "0ae890ef-fee9-4429-9c3b-402180129f61",
    "data": [
      {
        "text": "I\u0027ll be back",
        "userDefined": false
      }
    ],
    "isTemplate": false,
    "count": 0,
    "updated": 0
  },
  {
    "id": "5f44c6e2-9369-45d9-b9f8-b7340a8f5912",
    "data": [
      {
        "text": "I promise to ",
        "userDefined": false
      },
      {
        "text": "come",
        "meta": "@sys.ignore",
        "userDefined": false
      },
      {
        "text": " back",
        "userDefined": false
      }
    ],
    "isTemplate": false,
    "count": 0,
    "updated": 0
  }
]