[
  {
    "id": "12bd649d-0466-497f-b208-73bad6a5e082",
    "data": [
      {
        "text": "I\u0027m waiting",
        "userDefined": false
      }
    ],
    "isTemplate": false,
    "count": 0,
    "updated": 0
  },
  {
    "id": "8379ce37-9ed8-4233-b146-dc323a7b0283",
    "data": [
      {
        "text": "still waiting",
        "userDefined": false
      }
    ],
    "isTemplate": false,
    "count": 0,
    "updated": 0
  },
  {
    "id": "69464aaa-f6f8-423d-9fc2-ecb87725c81d",
    "data": [
      {
        "text": "I can\u0027t wait anymore",
        "userDefined": false
      }
    ],
    "isTemplate": false,
    "count": 0,
    "updated": 0
  },
  {
    "id": "c4ce2702-a5a5-423e-a97e-ed1bd17e27fb",
    "data": [
      {
        "text": "how long do I have to wait",
        "userDefined": false
      }
    ],
    "isTemplate": false,
    "count": 0,
    "updated": 0
  },
  {
    "id": "bdf7947b-8112-4aed-81a2-e6a1d922afbd",
    "data": [
      {
        "text": "I\u0027ll wait",
        "userDefined": false
      }
    ],
    "isTemplate": false,
    "count": 0,
    "updated": 0
  }
]